invenio_sitemap/__init__.py
invenio_sitemap/cache.py
invenio_sitemap/config.py
invenio_sitemap/ext.py
invenio_sitemap/sitemap.py
invenio_sitemap/tasks.py
invenio_sitemap/utils.py
invenio_sitemap/views.py
invenio_sitemap/templates/invenio_sitemap/sitemap.xml
invenio_sitemap/templates/invenio_sitemap/sitemap_index.xml
invenio_sitemap-0.3.0.dist-info/licenses/AUTHORS.rst
invenio_sitemap-0.3.0.dist-info/licenses/LICENSE
invenio_sitemap-0.3.0.dist-info/METADATA
invenio_sitemap-0.3.0.dist-info/WHEEL
invenio_sitemap-0.3.0.dist-info/entry_points.txt
invenio_sitemap-0.3.0.dist-info/top_level.txt
invenio_sitemap-0.3.0.dist-info/RECORD
