Metadata-Version: 2.4
Name: invenio-sitemap
Version: 0.3.0
Summary: Sitemap indices and Sitemaps for InvenioRDM
Author-email: Northwestern University <DL_FSM_GDS@e.northwestern.edu>
License: MIT License
Project-URL: Repository, https://github.com/inveniosoftware/invenio-sitemap
Keywords: invenio,inveniordm,rdm,sitemap
Classifier: Environment :: Web Environment
Classifier: Intended Audience :: Developers
Classifier: License :: OSI Approved :: MIT License
Classifier: Operating System :: OS Independent
Classifier: Programming Language :: Python
Classifier: Topic :: Internet :: WWW/HTTP :: Dynamic Content
Classifier: Topic :: Software Development :: Libraries :: Python Modules
Classifier: Programming Language :: Python :: 3
Classifier: Programming Language :: Python :: 3.9
Classifier: Programming Language :: Python :: 3.10
Classifier: Programming Language :: Python :: 3.11
Classifier: Programming Language :: Python :: 3.12
Classifier: Programming Language :: Python :: 3.13
Requires-Python: >=3.9
License-File: LICENSE
License-File: AUTHORS.rst
Requires-Dist: arrow>=0.17.0
Requires-Dist: invenio-base<3.0.0,>=2.1.0
Requires-Dist: invenio-cache<3.0.0,>=2.0.0
Requires-Dist: invenio-celery<3.0.0,>=2.0.0
Provides-Extra: tests
Requires-Dist: check-manifest>=0.49; extra == "tests"
Requires-Dist: invenio-app<3.0.0,>=2.1.0; extra == "tests"
Requires-Dist: invenio-db[postgresql]<3.0.0,>=2.0.0; extra == "tests"
Requires-Dist: invenio-search[opensearch2]<4.0.0,>=3.0.0; extra == "tests"
Requires-Dist: pytest-black-ng>=0.4.0; extra == "tests"
Requires-Dist: pytest-invenio<4.0.0,>=3.2.0; extra == "tests"
Requires-Dist: sphinx>=4.5.0; extra == "tests"
Requires-Dist: xmlschema<4.0.0,>=3.4.0; extra == "tests"
Dynamic: license-file
